[
  {
    "team": "Baltimore Orioles",
    "league": "MLB",
    "conference": "American League",
    "division": "AL East",
    "founded": 1901,
    "city": "Baltimore",
    "state": "Maryland",
    "stadium": "Oriole Park at Camden Yards",
    "championships": 3,
    "playoff_appearances": 19,
    "colors": ["#DF4601", "#000000", "#FFFFFF"],
    "notes": "Won World Series in 1966, 1970, 1983"
  },
  {
    "team": "Boston Red Sox",
    "league": "MLB",
    "conference": "American League",
    "division": "AL East",
    "founded": 1901,
    "city": "Boston",
    "state": "Massachusetts",
    "stadium": "Fenway Park",
    "championships": 9,
    "playoff_appearances": 24,
    "colors": ["#BD3039", "#0C2340", "#FFFFFF"],
    "notes": "Won World Series in 1903, 1912, 1915, 1916, 1918, 2004, 2007, 2013, 2018"
  },
  {
    "team": "New York Yankees",
    "league": "MLB",
    "conference": "American League",
    "division": "AL East",
    "founded": 1901,
    "city": "New York",
    "state": "New York",
    "stadium": "Yankee Stadium",
    "championships": 27,
    "playoff_appearances": 58,
    "colors": ["#003087", "#E4002C", "#FFFFFF"],
    "notes": "Most successful MLB franchise with 27 World Series championships"
  },
  {
    "team": "Tampa Bay Rays",
    "league": "MLB",
    "conference": "American League",
    "division": "AL East",
    "founded": 1998,
    "city": "St. Petersburg",
    "state": "Florida",
    "stadium": "Tropicana Field",
    "championships": 0,
    "playoff_appearances": 8,
    "colors": ["#092C5C", "#8FBCE6", "#F5D130"],
    "notes": "Never won a World Series"
  },
  {
    "team": "Toronto Blue Jays",
    "league": "MLB",
    "conference": "American League",
    "division": "AL East",
    "founded": 1977,
    "city": "Toronto",
    "state": "Ontario",
    "stadium": "Rogers Centre",
    "championships": 2,
    "playoff_appearances": 8,
    "colors": ["#134A8E", "#E8291C", "#FFFFFF"],
    "notes": "Won World Series in 1992, 1993"
  },
  {
    "team": "Chicago White Sox",
    "league": "MLB",
    "conference": "American League",
    "division": "AL Central",
    "founded": 1901,
    "city": "Chicago",
    "state": "Illinois",
    "stadium": "Guaranteed Rate Field",
    "championships": 3,
    "playoff_appearances": 11,
    "colors": ["#27251F", "#C4CED4", "#FFFFFF"],
    "notes": "Won World Series in 1906, 1917, 2005"
  },
  {
    "team": "Cleveland Guardians",
    "league": "MLB",
    "conference": "American League",
    "division": "AL Central",
    "founded": 1901,
    "city": "Cleveland",
    "state": "Ohio",
    "stadium": "Progressive Field",
    "championships": 2,
    "playoff_appearances": 18,
    "colors": ["#E31937", "#002B5C", "#FFFFFF"],
    "notes": "Won World Series in 1920, 1948; known as Indians until 2021"
  },
  {
    "team": "Detroit Tigers",
    "league": "MLB",
    "conference": "American League",
    "division": "AL Central",
    "founded": 1901,
    "city": "Detroit",
    "state": "Michigan",
    "stadium": "Comerica Park",
    "championships": 4,
    "playoff_appearances": 16,
    "colors": ["#FA4616", "#0C2C56", "#FFFFFF"],
    "notes": "Won World Series in 1935, 1945, 1968, 1984"
  },
  {
    "team": "Kansas City Royals",
    "league": "MLB",
    "conference": "American League",
    "division": "AL Central",
    "founded": 1969,
    "city": "Kansas City",
    "state": "Missouri",
    "stadium": "Kauffman Stadium",
    "championships": 2,
    "playoff_appearances": 9,
    "colors": ["#004687", "#BD9B60", "#FFFFFF"],
    "notes": "Won World Series in 1985, 2015"
  },
  {
    "team": "Minnesota Twins",
    "league": "MLB",
    "conference": "American League",
    "division": "AL Central",
    "founded": 1901,
    "city": "Minneapolis",
    "state": "Minnesota",
    "stadium": "Target Field",
    "championships": 3,
    "playoff_appearances": 14,
    "colors": ["#002B5C", "#D31145", "#B9975B"],
    "notes": "Won World Series in 1924 (as Senators), 1987, 1991"
  },
  {
    "team": "Houston Astros",
    "league": "MLB",
    "conference": "American League",
    "division": "AL West",
    "founded": 1962,
    "city": "Houston",
    "state": "Texas",
    "stadium": "Minute Maid Park",
    "championships": 2,
    "playoff_appearances": 15,
    "colors": ["#002D62", "#EB6E1F", "#F4911E"],
    "notes": "Won World Series in 2017, 2022; moved from NL to AL in 2013"
  },
  {
    "team": "Los Angeles Angels",
    "league": "MLB",
    "conference": "American League",
    "division": "AL West",
    "founded": 1961,
    "city": "Anaheim",
    "state": "California",
    "stadium": "Angel Stadium",
    "championships": 1,
    "playoff_appearances": 10,
    "colors": ["#BA0021", "#003263", "#C4CED4"],
    "notes": "Won World Series in 2002"
  },
  {
    "team": "Oakland Athletics",
    "league": "MLB",
    "conference": "American League",
    "division": "AL West",
    "founded": 1901,
    "city": "Oakland",
    "state": "California",
    "stadium": "Oakland Coliseum",
    "championships": 9,
    "playoff_appearances": 21,
    "colors": ["#003831", "#EFB21E", "#FFFFFF"],
    "notes": "Won World Series in 1910, 1911, 1913, 1929, 1930, 1972, 1973, 1974, 1989"
  },
  {
    "team": "Seattle Mariners",
    "league": "MLB",
    "conference": "American League",
    "division": "AL West",
    "founded": 1977,
    "city": "Seattle",
    "state": "Washington",
    "stadium": "T-Mobile Park",
    "championships": 0,
    "playoff_appearances": 5,
    "colors": ["#0C2C56", "#005C5C", "#C4CED4"],
    "notes": "Never won a World Series"
  },
  {
    "team": "Texas Rangers",
    "league": "MLB",
    "conference": "American League",
    "division": "AL West",
    "founded": 1961,
    "city": "Arlington",
    "state": "Texas",
    "stadium": "Globe Life Field",
    "championships": 1,
    "playoff_appearances": 9,
    "colors": ["#003278", "#C0111F", "#FFFFFF"],
    "notes": "Won World Series in 2023; moved from Washington in 1972"
  },
  {
    "team": "Arizona Diamondbacks",
    "league": "MLB",
    "conference": "National League",
    "division": "NL West",
    "founded": 1998,
    "city": "Phoenix",
    "state": "Arizona",
    "stadium": "Chase Field",
    "championships": 1,
    "playoff_appearances": 6,
    "colors": ["#A71930", "#E3D4AD", "#000000"],
    "notes": "Won World Series in 2001"
  },
  {
    "team": "Colorado Rockies",
    "league": "MLB",
    "conference": "National League",
    "division": "NL West",
    "founded": 1993,
    "city": "Denver",
    "state": "Colorado",
    "stadium": "Coors Field",
    "championships": 0,
    "playoff_appearances": 5,
    "colors": ["#33006F", "#C4CED4", "#000000"],
    "notes": "Never won a World Series"
  },
  {
    "team": "Los Angeles Dodgers",
    "league": "MLB",
    "conference": "National League",
    "division": "NL West",
    "founded": 1883,
    "city": "Los Angeles",
    "state": "California",
    "stadium": "Dodger Stadium",
    "championships": 7,
    "playoff_appearances": 37,
    "colors": ["#005A9C", "#EF3E42", "#FFFFFF"],
    "notes": "Won World Series in 1955, 1959, 1963, 1965, 1981, 1988, 2020"
  },
  {
    "team": "San Diego Padres",
    "league": "MLB",
    "conference": "National League",
    "division": "NL West",
    "founded": 1969,
    "city": "San Diego",
    "state": "California",
    "stadium": "Petco Park",
    "championships": 0,
    "playoff_appearances": 7,
    "colors": ["#2F241D", "#FFC425", "#FFFFFF"],
    "notes": "Never won a World Series"
  },
  {
    "team": "San Francisco Giants",
    "league": "MLB",
    "conference": "National League",
    "division": "NL West",
    "founded": 1883,
    "city": "San Francisco",
    "state": "California",
    "stadium": "Oracle Park",
    "championships": 8,
    "playoff_appearances": 28,
    "colors": ["#FD5A1E", "#27251F", "#EFD19F"],
    "notes": "Won World Series in 1905, 1921, 1922, 1933, 1954, 2010, 2012, 2014"
  },
  {
    "team": "Atlanta Braves",
    "league": "MLB",
    "conference": "National League",
    "division": "NL East",
    "founded": 1871,
    "city": "Atlanta",
    "state": "Georgia",
    "stadium": "Truist Park",
    "championships": 4,
    "playoff_appearances": 24,
    "colors": ["#CE1141", "#13274F", "#FFFFFF"],
    "notes": "Won World Series in 1914 (Boston), 1957 (Milwaukee), 1995, 2021"
  },
  {
    "team": "Miami Marlins",
    "league": "MLB",
    "conference": "National League",
    "division": "NL East",
    "founded": 1993,
    "city": "Miami",
    "state": "Florida",
    "stadium": "loanDepot park",
    "championships": 2,
    "playoff_appearances": 3,
    "colors": ["#00A3E0", "#EF3340", "#000000"],
    "notes": "Won World Series in 1997, 2003"
  },
  {
    "team": "New York Mets",
    "league": "MLB",
    "conference": "National League",
    "division": "NL East",
    "founded": 1962,
    "city": "New York",
    "state": "New York",
    "stadium": "Citi Field",
    "championships": 2,
    "playoff_appearances": 10,
    "colors": ["#002D72", "#FF5910", "#FFFFFF"],
    "notes": "Won World Series in 1969, 1986"
  },
  {
    "team": "Philadelphia Phillies",
    "league": "MLB",
    "conference": "National League",
    "division": "NL East",
    "founded": 1883,
    "city": "Philadelphia",
    "state": "Pennsylvania",
    "stadium": "Citizens Bank Park",
    "championships": 2,
    "playoff_appearances": 15,
    "colors": ["#E81828", "#002D72", "#FFFFFF"],
    "notes": "Won World Series in 1980, 2008"
  },
  {
    "team": "Washington Nationals",
    "league": "MLB",
    "conference": "National League",
    "division": "NL East",
    "founded": 1969,
    "city": "Washington",
    "state": "D.C.",
    "stadium": "Nationals Park",
    "championships": 1,
    "playoff_appearances": 6,
    "colors": ["#AB0003", "#14225A", "#FFFFFF"],
    "notes": "Won World Series in 2019; moved from Montreal in 2005"
  },
  {
    "team": "Chicago Cubs",
    "league": "MLB",
    "conference": "National League",
    "division": "NL Central",
    "founded": 1876,
    "city": "Chicago",
    "state": "Illinois",
    "stadium": "Wrigley Field",
    "championships": 3,
    "playoff_appearances": 22,
    "colors": ["#0E3386", "#CC3433", "#FFFFFF"],
    "notes": "Won World Series in 1907, 1908, 2016"
  },
  {
    "team": "Cincinnati Reds",
    "league": "MLB",
    "conference": "National League",
    "division": "NL Central",
    "founded": 1881,
    "city": "Cincinnati",
    "state": "Ohio",
    "stadium": "Great American Ball Park",
    "championships": 5,
    "playoff_appearances": 15,
    "colors": ["#C6011F", "#000000", "#FFFFFF"],
    "notes": "Won World Series in 1919, 1940, 1975, 1976, 1990"
  },
  {
    "team": "Milwaukee Brewers",
    "league": "MLB",
    "conference": "National League",
    "division": "NL Central",
    "founded": 1969,
    "city": "Milwaukee",
    "state": "Wisconsin",
    "stadium": "American Family Field",
    "championships": 0,
    "playoff_appearances": 7,
    "colors": ["#0A2351", "#B6922E", "#FFFFFF"],
    "notes": "Never won a World Series; moved from AL to NL in 1998"
  },
  {
    "team": "Pittsburgh Pirates",
    "league": "MLB",
    "conference": "National League",
    "division": "NL Central",
    "founded": 1881,
    "city": "Pittsburgh",
    "state": "Pennsylvania",
    "stadium": "PNC Park",
    "championships": 5,
    "playoff_appearances": 17,
    "colors": ["#FDB827", "#27251F", "#FFFFFF"],
    "notes": "Won World Series in 1909, 1925, 1960, 1971, 1979"
  },
  {
    "team": "St. Louis Cardinals",
    "league": "MLB",
    "conference": "National League",
    "division": "NL Central",
    "founded": 1882,
    "city": "St. Louis",
    "state": "Missouri",
    "stadium": "Busch Stadium",
    "championships": 11,
    "playoff_appearances": 32,
    "colors": ["#C41E3A", "#0C2340", "#FEDB00"],
    "notes": "Second-most World Series championships; won in 1926, 1931, 1934, 1942, 1944, 1946, 1964, 1967, 1982, 2006, 2011"
  }
]